aeqtl/__init__.py
aeqtl/aeqtl.py
aeqtl-0.1.0.dist-info/LICENSE
aeqtl-0.1.0.dist-info/METADATA
aeqtl-0.1.0.dist-info/WHEEL
aeqtl-0.1.0.dist-info/entry_points.txt
aeqtl-0.1.0.dist-info/top_level.txt
aeqtl-0.1.0.dist-info/RECORD
