Metadata-Version: 2.1
Name: aeqtl
Version: 0.1.0
Summary: eQTL analysis using region-based aggregation of rare variants.
Home-page: https://github.com/Huang-lab/AeQTL
Author: Guanlan Dong
Author-email: guanlan.dong@wustl.edu
License: UNKNOWN
Platform: UNKNOWN
Classifier: Programming Language :: Python :: 3
Classifier: License :: OSI Approved :: MIT License
Classifier: Operating System :: OS Independent
Requires-Dist: pysam (==0.13)
Requires-Dist: PyVCF
Requires-Dist: Cython
Requires-Dist: statsmodels
Requires-Dist: scipy
Requires-Dist: pandas
Requires-Dist: bx-interval-tree
